{"ongoing_trials": {}, "hyperparameters": {"space": [{"class_name": "Int", "config": {"name": "conv_0", "default": 16, "conditions": [], "min_value": 8, "max_value": 64, "step": 8, "sampling": "linear"}}, {"class_name": "Float", "config": {"name": "dropout_0", "default": 0.5, "conditions": [], "min_value": 0.1, "max_value": 0.8, "step": 0.1, "sampling": "linear"}}, {"class_name": "Int", "config": {"name": "conv_1", "default": 32, "conditions": [], "min_value": 16, "max_value": 128, "step": 8, "sampling": "linear"}}, {"class_name": "Float", "config": {"name": "dropout_1", "default": 0.5, "conditions": [], "min_value": 0.1, "max_value": 0.8, "step": 0.1, "sampling": "linear"}}, {"class_name": "Int", "config": {"name": "lstm_0", "default": 32, "conditions": [], "min_value": 8, "max_value": 64, "step": 8, "sampling": "linear"}}, {"class_name": "Int", "config": {"name": "lstm_1", "default": 16, "conditions": [], "min_value": 8, "max_value": 32, "step": 8, "sampling": "linear"}}, {"class_name": "Int", "config": {"name": "dense_0", "default": 128, "conditions": [], "min_value": 32, "max_value": 256, "step": 8, "sampling": "linear"}}, {"class_name": "Float", "config": {"name": "dropout_2", "default": 0.5, "conditions": [], "min_value": 0.1, "max_value": 0.8, "step": 0.1, "sampling": "linear"}}, {"class_name": "Int", "config": {"name": "dense_1", "default": 64, "conditions": [], "min_value": 16, "max_value": 128, "step": 8, "sampling": "linear"}}, {"class_name": "Float", "config": {"name": "dropout_3", "default": 0.5, "conditions": [], "min_value": 0.1, "max_value": 0.8, "step": 0.1, "sampling": "linear"}}, {"class_name": "Float", "config": {"name": "learning_rate", "default": 0.001, "conditions": [], "min_value": 1e-05, "max_value": 0.001, "step": null, "sampling": "log"}}], "values": {"conv_0": 16, "dropout_0": 0.5, "conv_1": 32, "dropout_1": 0.5, "lstm_0": 32, "lstm_1": 16, "dense_0": 128, "dropout_2": 0.5, "dense_1": 64, "dropout_3": 0.5, "learning_rate": 0.001}}, "start_order": ["00", "01", "02", "03", "04", "05", "06", "07", "08", "09", "10", "11", "12", "13", "14", "15", "16", "17", "18", "19"], "end_order": ["00", "01", "02", "03", "04", "05", "06", "07", "08", "09", "10", "11", "12", "13", "14", "15", "16", "17", "18", "19"], "run_times": {"00": 1, "01": 1, "02": 1, "03": 1, "04": 1, "05": 1, "06": 1, "07": 1, "08": 1, "09": 1, "10": 1, "11": 1, "12": 1, "13": 1, "14": 1, "15": 1, "16": 1, "17": 1, "18": 1, "19": 1}, "retry_queue": [], "seed": 1459, "seed_state": 1679, "tried_so_far": ["77e9f7ea5b073dcfd00fc9e64f29a483", "89dcbd38471776dd11d8ab886b81079e", "34c52f22b0f897b739b20e0f2b87c3a4", "f939cc8d8724d5481768914bd39a47bb", "6c29486aff26ad3de28ea7c4c55c10ee", "e3611a0af3d40fe20270824ce3616ca2", "a89ab457b6ce28c51263cb77b3d4853d", "93c92fc512dfcc8c8ba3ee3c0cef6d31", "308b66fdc2a4159a8d42e96a23a328e4", "aa16e4e10be682e712283e27f5f59971", "aa68ad0253be27215964f4896e90504c", "d675bc565515d00d11c63724ea820dae", "4252f1945044cd673a6abe534bc68a16", "b1f005614afce54f4d4b6084b83c5f25", "517902b1a3f1cebdc2a0defc60805223", "fe7f529ee637a5fdb0e2800799fb9dde", "a168343a9a47166080d9cc35e9bbddec", "7a9db38f81faed97aac21f61580e05b2", "ff4f87f2bb6c0335727eea1cc00fc5fd", "260e356a4c32a7ba332e22d860577bf6"], "id_to_hash": {"00": "f939cc8d8724d5481768914bd39a47bb", "01": "517902b1a3f1cebdc2a0defc60805223", "02": "aa68ad0253be27215964f4896e90504c", "03": "4252f1945044cd673a6abe534bc68a16", "04": "d675bc565515d00d11c63724ea820dae", "05": "34c52f22b0f897b739b20e0f2b87c3a4", "06": "fe7f529ee637a5fdb0e2800799fb9dde", "07": "308b66fdc2a4159a8d42e96a23a328e4", "08": "ff4f87f2bb6c0335727eea1cc00fc5fd", "09": "e3611a0af3d40fe20270824ce3616ca2", "10": "260e356a4c32a7ba332e22d860577bf6", "11": "77e9f7ea5b073dcfd00fc9e64f29a483", "12": "aa16e4e10be682e712283e27f5f59971", "13": "a89ab457b6ce28c51263cb77b3d4853d", "14": "6c29486aff26ad3de28ea7c4c55c10ee", "15": "93c92fc512dfcc8c8ba3ee3c0cef6d31", "16": "a168343a9a47166080d9cc35e9bbddec", "17": "7a9db38f81faed97aac21f61580e05b2", "18": "b1f005614afce54f4d4b6084b83c5f25", "19": "89dcbd38471776dd11d8ab886b81079e"}, "display": {"search_start": "2024-07-29T09:50:32.905754", "trial_start": {"00": "2024-07-29T09:50:32.905754", "01": "2024-07-29T09:51:32.913414", "02": "2024-07-29T09:52:37.093836", "03": "2024-07-29T09:53:31.326716", "04": "2024-07-29T09:54:37.300404", "05": "2024-07-29T09:55:35.871362", "06": "2024-07-29T09:56:26.189129", "07": "2024-07-29T09:57:33.689217", "08": "2024-07-29T09:58:39.496743", "09": "2024-07-29T09:59:51.859740", "10": "2024-07-29T10:01:02.161000", "11": "2024-07-29T10:02:05.796326", "12": "2024-07-29T10:03:16.530079", "13": "2024-07-29T10:04:21.958340", "14": "2024-07-29T10:05:29.194454", "15": "2024-07-29T10:06:32.046827", "16": "2024-07-29T10:07:25.626969", "17": "2024-07-29T10:08:33.568524", "18": "2024-07-29T10:09:28.880998", "19": "2024-07-29T10:10:34.365283"}, "trial_number": {"00": 1, "01": 2, "02": 3, "03": 4, "04": 5, "05": 6, "06": 7, "07": 8, "08": 9, "09": 10, "10": 11, "11": 12, "12": 13, "13": 14, "14": 15, "15": 16, "16": 17, "17": 18, "18": 19, "19": 20}}, "num_initial_points": null, "alpha": 0.0001, "beta": 2.6}